MANIFEST.in
README.md
UNLICENSE
setup.py
assets/turtle-sketch.jpg
docs/Makefile
docs/api.rst
docs/changelog.rst
docs/conf.py
docs/contributing.rst
docs/help.rst
docs/index.rst
docs/quickstart.rst
docs/upgrading.rst
docs/_static/flask-simple-small.jpg
docs/_static/flask-simple.png
docs/_templates/sidebarintro.html
docs/_templates/sidebarlogo.html
docs/_themes/.git
docs/_themes/.gitignore
docs/_themes/LICENSE
docs/_themes/README
docs/_themes/flask_theme_support.py
docs/_themes/flask/layout.html
docs/_themes/flask/relations.html
docs/_themes/flask/theme.conf
docs/_themes/flask/static/flasky.css_t
docs/_themes/flask_small/layout.html
docs/_themes/flask_small/theme.conf
docs/_themes/flask_small/static/flasky.css_t
flask_simple/__init__.py
flask_simple/errors.py
flask_simple/manager.py
flask_simple.egg-info/PKG-INFO
flask_simple.egg-info/SOURCES.txt
flask_simple.egg-info/dependency_links.txt
flask_simple.egg-info/not-zip-safe
flask_simple.egg-info/requires.txt
flask_simple.egg-info/top_level.txt