Metadata-Version: 1.1
Name: flask-simple
Version: 0.0.1
Summary: SimpleDB integration for Flask.
Home-page: https://github.com/rdegges/flask-simple
Author: Randall Degges
Author-email: r@rdegges.com
License: UNLICENSE
Keywords: python simpledb dynamo aws amazon flask web database
Platform: any
Classifier: Environment :: Web Environment
Classifier: Intended Audience :: Developers
Classifier: License :: Public Domain
Classifier: Operating System :: OS Independent
Classifier: Programming Language :: Python
Classifier: Topic :: Internet :: WWW/HTTP :: Dynamic Content
Classifier: Topic :: Software Development :: Libraries :: Python Modules
Classifier: Topic :: Database
Classifier: Programming Language :: Python
Classifier: Programming Language :: Python :: 2
Classifier: Programming Language :: Python :: 2.7
Classifier: Programming Language :: Python :: Implementation :: PyPy
